{"last_node_id":38,"last_link_id":60,"nodes":[{"id":6,"type":"Reroute","pos":[-112,-14],"size":[75,26],"flags":{},"order":7,"mode":0,"inputs":[{"name":"","type":"*","link":5,"label":""}],"outputs":[{"name":"","type":"IMAGE","links":[6],"slot_index":0,"label":""}],"properties":{"showOutputText":false,"horizontal":false}},{"id":10,"type":"CLIPSetLastLayer","pos":[-681,343],"size":{"0":315,"1":58},"flags":{},"order":12,"mode":0,"inputs":[{"name":"clip","type":"CLIP","link":29,"label":"clip"}],"outputs":[{"name":"CLIP","type":"CLIP","links":[11,13],"shape":3,"label":"CLIP","slot_index":0}],"properties":{"Node name for S&R":"CLIPSetLastLayer"},"widgets_values":[-2],"serialize_values":[null]},{"id":17,"type":"PreviewImage","pos":[813,150],"size":{"0":210,"1":246},"flags":{},"order":19,"mode":0,"inputs":[{"name":"images","type":"IMAGE","link":24,"label":"images"}],"properties":{"Node name for S&R":"PreviewImage"}},{"id":14,"type":"LoraLoaderModelOnly","pos":[-687,443],"size":{"0":315,"1":82},"flags":{},"order":11,"mode":0,"inputs":[{"name":"model","type":"MODEL","link":28,"label":"model","slot_index":0}],"outputs":[{"name":"MODEL","type":"MODEL","links":[18],"shape":3,"label":"MODEL","slot_index":0}],"properties":{"Node name for S&R":"LoraLoaderModelOnly"},"widgets_values":["ip-adapter-faceid-plusv2_sd15_lora(plusv2)",1],"serialize_values":["3295_4973_5831@8abff87a15",null]},{"id":5,"type":"LoadImage","pos":[-676,-171],"size":{"0":315,"1":314},"flags":{},"order":0,"mode":0,"outputs":[{"name":"IMAGE","type":"IMAGE","links":[5],"shape":3,"label":"IMAGE","slot_index":0},{"name":"MASK","type":"MASK","links":null,"shape":3,"label":"MASK"}],"properties":{"Node name for S&R":"LoadImage"},"widgets_values":["https://bfs.esheep.com/bfs/aikobo-bfs/app/comfy/b3b5c9bcf870b1a88a6cad7e06cdca94cf527ef6.jpg","image"],"serialize_values":[null,null]},{"id":2,"type":"IPAdapterModelLoader","pos":[-692,569],"size":{"0":315,"1":58},"flags":{},"order":1,"mode":0,"outputs":[{"name":"IPADAPTER","type":"IPADAPTER","links":[1],"shape":3,"label":"IPADAPTER"}],"properties":{"Node name for S&R":"IPAdapterModelLoader"},"widgets_values":["ip-adapter-faceid-plusv2_sd15.bin"],"serialize_values":[null]},{"id":3,"type":"CLIPVisionLoader","pos":[-681,674],"size":{"0":315,"1":58},"flags":{},"order":2,"mode":0,"outputs":[{"name":"CLIP_VISION","type":"CLIP_VISION","links":[2],"shape":3,"label":"CLIP_VISION"}],"properties":{"Node name for S&R":"CLIPVisionLoader"},"widgets_values":["ip_adaptor_sd15_pytorch_model.bin"],"serialize_values":[null]},{"id":4,"type":"InsightFaceLoader","pos":[-688,789],"size":{"0":315,"1":58},"flags":{},"order":3,"mode":0,"outputs":[{"name":"INSIGHTFACE","type":"INSIGHTFACE","links":[3],"shape":3,"label":"INSIGHTFACE"}],"properties":{"Node name for S&R":"InsightFaceLoader"},"widgets_values":["CPU"],"serialize_values":[null]},{"id":11,"type":"KSampler","pos":[401,37],"size":{"0":315,"1":262},"flags":{},"order":16,"mode":0,"inputs":[{"name":"model","type":"MODEL","link":22,"label":"model"},{"name":"positive","type":"CONDITIONING","link":12,"label":"positive"},{"name":"negative","type":"CONDITIONING","link":14,"label":"negative"},{"name":"latent_image","type":"LATENT","link":25,"label":"latent_image","slot_index":3}],"outputs":[{"name":"LATENT","type":"LATENT","links":[19,35],"shape":3,"label":"LATENT","slot_index":0}],"properties":{"Node name for S&R":"KSampler"},"widgets_values":[1066205558833256,"randomize",30,7.04,"ddim","ddim_uniform",1],"serialize_values":[null,null,null,null,null,null,null]},{"id":19,"type":"LoraLoader","pos":[-345,350],"size":{"0":315,"1":126},"flags":{},"order":10,"mode":4,"inputs":[{"name":"model","type":"MODEL","link":32,"label":"model"},{"name":"clip","type":"CLIP","link":33,"label":"clip"}],"outputs":[{"name":"MODEL","type":"MODEL","links":[28],"shape":3,"label":"MODEL"},{"name":"CLIP","type":"CLIP","links":[29],"shape":3,"label":"CLIP"}],"properties":{"Node name for S&R":"LoraLoader"},"widgets_values":["LEOSAM's FilmGirl 胶片风 Film Grain LoRA(VELVIA 3.0)",0.65,0.65],"serialize_values":["207_1727_2085@ac8b0e4aa7",null,null]},{"id":22,"type":"LatentUpscaleBy","pos":[403,513],"size":{"0":315,"1":82},"flags":{},"order":18,"mode":0,"inputs":[{"name":"samples","type":"LATENT","link":35,"label":"samples"}],"outputs":[{"name":"LATENT","type":"LATENT","links":[36],"shape":3,"label":"LATENT","slot_index":0}],"properties":{"Node name for S&R":"LatentUpscaleBy"},"widgets_values":["nearest-exact",1.75],"serialize_values":[null,null]},{"id":18,"type":"EmptyLatentImage","pos":[400,365],"size":{"0":315,"1":106},"flags":{},"order":4,"mode":0,"outputs":[{"name":"LATENT","type":"LATENT","links":[25],"shape":3,"label":"LATENT"}],"properties":{"Node name for S&R":"EmptyLatentImage"},"widgets_values":[512,768,1],"serialize_values":[null,null,null]},{"id":15,"type":"VAEDecode","pos":[813,54],"size":{"0":210,"1":46},"flags":{},"order":17,"mode":0,"inputs":[{"name":"samples","type":"LATENT","link":19,"label":"samples"},{"name":"vae","type":"VAE","link":23,"label":"vae","slot_index":1}],"outputs":[{"name":"IMAGE","type":"IMAGE","links":[24],"shape":3,"label":"IMAGE","slot_index":0}],"properties":{"Node name for S&R":"VAEDecode"}},{"id":1,"type":"IPAdapterApplyFaceID","pos":[10,411],"size":{"0":315,"1":326},"flags":{},"order":13,"mode":0,"inputs":[{"name":"ipadapter","type":"IPADAPTER","link":1,"label":"ipadapter","slot_index":0},{"name":"clip_vision","type":"CLIP_VISION","link":2,"label":"clip_vision","slot_index":1},{"name":"insightface","type":"INSIGHTFACE","link":3,"label":"insightface","slot_index":2},{"name":"image","type":"IMAGE","link":6,"label":"image","slot_index":3},{"name":"model","type":"MODEL","link":18,"label":"model"},{"name":"attn_mask","type":"MASK","link":null,"label":"attn_mask"}],"outputs":[{"name":"MODEL","type":"MODEL","links":[22,37],"shape":3,"label":"MODEL","slot_index":0}],"properties":{"Node name for S&R":"IPAdapterApplyFaceID"},"widgets_values":[0.9500000000000001,0.1,"original",0,1,true,1,false],"serialize_values":[null,null,null,null,null,null,null,null]},{"id":30,"type":"Reroute","pos":[1366,438],"size":[75,26],"flags":{},"order":9,"mode":0,"inputs":[{"name":"","type":"*","link":49,"label":""}],"outputs":[{"name":"","type":"VAE","links":[],"slot_index":0,"label":""}],"properties":{"showOutputText":false,"horizontal":false}},{"id":35,"type":"PreviewImage","pos":[1504,480],"size":{"0":210,"1":246},"flags":{},"order":22,"mode":0,"inputs":[{"name":"images","type":"IMAGE","link":57,"label":"images"}],"properties":{"Node name for S&R":"PreviewImage"}},{"id":23,"type":"VAEDecode","pos":[1101,483],"size":{"0":210,"1":46},"flags":{},"order":21,"mode":0,"inputs":[{"name":"samples","type":"LATENT","link":40,"label":"samples"},{"name":"vae","type":"VAE","link":41,"label":"vae"}],"outputs":[{"name":"IMAGE","type":"IMAGE","links":[57,58],"shape":3,"label":"IMAGE","slot_index":0}],"properties":{"Node name for S&R":"VAEDecode"}},{"id":37,"type":"LoadImage","pos":[412,673],"size":{"0":315,"1":314},"flags":{},"order":5,"mode":0,"outputs":[{"name":"IMAGE","type":"IMAGE","links":[59],"shape":3,"label":"IMAGE"},{"name":"MASK","type":"MASK","links":null,"shape":3,"label":"MASK"}],"properties":{"Node name for S&R":"LoadImage"},"widgets_values":["https://bfs.esheep.com/bfs/aikobo-bfs/app/comfy/b3b5c9bcf870b1a88a6cad7e06cdca94cf527ef6.jpg","image"],"serialize_values":[null,null]},{"id":38,"type":"PreviewImage","pos":[1734,482],"size":{"0":210,"1":246},"flags":{},"order":24,"mode":0,"inputs":[{"name":"images","type":"IMAGE","link":60,"label":"images"}],"properties":{"Node name for S&R":"PreviewImage"}},{"id":36,"type":"ReActorFaceSwap","pos":[1124.56214868164,649.4090034179685],"size":{"0":315,"1":338},"flags":{},"order":23,"mode":0,"inputs":[{"name":"input_image","type":"IMAGE","link":58,"label":"input_image"},{"name":"source_image","type":"IMAGE","link":59,"label":"source_image","slot_index":1},{"name":"face_model","type":"FACE_MODEL","link":null,"label":"face_model"}],"outputs":[{"name":"IMAGE","type":"IMAGE","links":[60],"shape":3,"label":"IMAGE","slot_index":0},{"name":"FACE_MODEL","type":"FACE_MODEL","links":null,"shape":3,"label":"FACE_MODEL"}],"properties":{"Node name for S&R":"ReActorFaceSwap"},"widgets_values":[true,"inswapper_128.onnx","retinaface_resnet50","codeformer.pth",1,0.5,"no","no","0","0",1],"serialize_values":[null,null,null,null,null,null,null,null,null,null,null]},{"id":7,"type":"CheckpointLoaderSimple","pos":[-684,199],"size":{"0":315,"1":98},"flags":{},"order":6,"mode":0,"outputs":[{"name":"MODEL","type":"MODEL","links":[30],"shape":3,"label":"MODEL","slot_index":0},{"name":"CLIP","type":"CLIP","links":[31],"shape":3,"label":"CLIP","slot_index":1},{"name":"VAE","type":"VAE","links":[23,41,49],"shape":3,"label":"VAE","slot_index":2}],"properties":{"Node name for S&R":"CheckpointLoaderSimple"},"widgets_values":["墨幽人造人(v1080-none)"],"serialize_values":["833_4584_5364@d196f0825b.safetensors"]},{"id":21,"type":"KSampler","pos":[765,455],"size":{"0":315,"1":262},"flags":{},"order":20,"mode":0,"inputs":[{"name":"model","type":"MODEL","link":37,"label":"model"},{"name":"positive","type":"CONDITIONING","link":38,"label":"positive","slot_index":1},{"name":"negative","type":"CONDITIONING","link":39,"label":"negative","slot_index":2},{"name":"latent_image","type":"LATENT","link":36,"label":"latent_image"}],"outputs":[{"name":"LATENT","type":"LATENT","links":[40],"shape":3,"label":"LATENT","slot_index":0}],"properties":{"Node name for S&R":"KSampler"},"widgets_values":[905476097332617,"randomize",10,6.5,"ddim","ddim_uniform",0.4],"serialize_values":[null,null,null,null,null,null,null]},{"id":13,"type":"BNK_CLIPTextEncodeAdvanced","pos":[17,203],"size":{"0":320.6074523925781,"1":148.72833251953125},"flags":{},"order":15,"mode":0,"inputs":[{"name":"clip","type":"CLIP","link":13,"label":"clip"}],"outputs":[{"name":"CONDITIONING","type":"CONDITIONING","links":[14,39],"shape":3,"label":"CONDITIONING","slot_index":0}],"properties":{"Node name for S&R":"BNK_CLIPTextEncodeAdvanced"},"widgets_values":[" text, watermark,deformed,nsfw,naked, blurry,lowres, (3d:1.1),painting,(cartoon:1.2),(low_quality:1.4),(worst_quality:1.4),(normal_quality:1.4),(blurry:1.5),(lowres:1.3),(bad anatomy:1.1),embedding:EasyNegativeV2, embedding:ng_deepnegative_v1_75t, (bad_hands:1.4), (deformed_face:1.2),(bad_face:1.1),from_side,","none","A1111"],"serialize_values":[" text, watermark,deformed,nsfw,naked, blurry,lowres, (3d:1.1),painting,(cartoon:1.2),(low_quality:1.4),(worst_quality:1.4),(normal_quality:1.4),(blurry:1.5),(lowres:1.3),(bad anatomy:1.1),embedding:EasyNegativeV2, embedding:ng_deepnegative_v1_75t, (bad_hands:1.4), (deformed_face:1.2),(bad_face:1.1),from_side,",null,null]},{"id":20,"type":"LoraLoader","pos":[-319,172],"size":{"0":315,"1":126},"flags":{},"order":8,"mode":4,"inputs":[{"name":"model","type":"MODEL","link":30,"label":"model"},{"name":"clip","type":"CLIP","link":31,"label":"clip"}],"outputs":[{"name":"MODEL","type":"MODEL","links":[32],"shape":3,"label":"MODEL"},{"name":"CLIP","type":"CLIP","links":[33],"shape":3,"label":"CLIP"}],"properties":{"Node name for S&R":"LoraLoader"},"widgets_values":["Lolita fashion dress | 洛丽塔裙子(Classic style 4)",0.28,0.28],"serialize_values":["241_4923_5758@4185a2af76",null,null]},{"id":12,"type":"BNK_CLIPTextEncodeAdvanced","pos":[18,10],"size":{"0":320.6074523925781,"1":148.72833251953125},"flags":{},"order":14,"mode":0,"inputs":[{"name":"clip","type":"CLIP","link":11,"label":"clip"}],"outputs":[{"name":"CONDITIONING","type":"CONDITIONING","links":[12,38],"shape":3,"label":"CONDITIONING","slot_index":0}],"properties":{"Node name for S&R":"BNK_CLIPTextEncodeAdvanced"},"widgets_values":["1girl,solo,detailed face and eyes,{masterpiece,highres,best quality,detailed},(extremely detailed 8k wallpaper,highres) ,(8k,best_quality,masterpiece:1.2),ultra-detailed,Masterpiece,(film_grain:1.25),(photorealistic:1.3),polaroid,  \nmakeup,(unmatured girl,teen,petite,cute,lovely:1.1),eyelashes,\n(detailed face and eyes:1.15),\nlolita,","none","A1111"],"serialize_values":["1girl,solo,detailed face and eyes,masterpiece,highres,best quality,detailed,(extremely detailed 8k wallpaper,highres) ,(8k,best_quality,masterpiece:1.2),ultra-detailed,Masterpiece,(film_grain:1.25),(photorealistic:1.3),polaroid,  \nmakeup,(unmatured girl,teen,petite,cute,lovely:1.1),eyelashes,\n(detailed face and eyes:1.15),\nlolita,",null,null]}],"links":[[1,2,0,1,0,"IPADAPTER"],[2,3,0,1,1,"CLIP_VISION"],[3,4,0,1,2,"INSIGHTFACE"],[5,5,0,6,0,"*"],[6,6,0,1,3,"IMAGE"],[11,10,0,12,0,"CLIP"],[12,12,0,11,1,"CONDITIONING"],[13,10,0,13,0,"CLIP"],[14,13,0,11,2,"CONDITIONING"],[18,14,0,1,4,"MODEL"],[19,11,0,15,0,"LATENT"],[22,1,0,11,0,"MODEL"],[23,7,2,15,1,"VAE"],[24,15,0,17,0,"IMAGE"],[25,18,0,11,3,"LATENT"],[28,19,0,14,0,"MODEL"],[29,19,1,10,0,"CLIP"],[30,7,0,20,0,"MODEL"],[31,7,1,20,1,"CLIP"],[32,20,0,19,0,"MODEL"],[33,20,1,19,1,"CLIP"],[35,11,0,22,0,"LATENT"],[36,22,0,21,3,"LATENT"],[37,1,0,21,0,"MODEL"],[38,12,0,21,1,"CONDITIONING"],[39,13,0,21,2,"CONDITIONING"],[40,21,0,23,0,"LATENT"],[41,7,2,23,1,"VAE"],[49,7,2,30,0,"*"],[57,23,0,35,0,"IMAGE"],[58,23,0,36,0,"IMAGE"],[59,37,0,36,1,"IMAGE"],[60,36,0,38,0,"IMAGE"]],"groups":[],"config":{},"extra":{},"version":0.4}