{"last_node_id": 117, "last_link_id": 229, "nodes": [{"id": 15, "type": "ImageOnlyCheckpointLoader", "pos": [177.24009997558596, 308.9400007324219], "size": {"0": 369.6000061035156, "1": 98}, "flags": {}, "order": 0, "mode": 0, "outputs": [{"name": "MODEL", "type": "MODEL", "links": [61], "shape": 3, "slot_index": 0, "label": "\u6a21\u578b"}, {"name": "CLIP_VISION", "type": "CLIP_VISION", "links": [50], "shape": 3, "slot_index": 1, "label": "CLIP\u89c6\u89c9"}, {"name": "VAE", "type": "VAE", "links": [26, 52], "shape": 3, "slot_index": 2, "label": "VAE"}], "properties": {"Node name for S&R": "ImageOnlyCheckpointLoader"}, "widgets_values": ["stable_zero123.ckpt"]}, {"id": 32, "type": "PrimitiveNode", "pos": [195.24009997558602, 686.9400007324214], "size": {"0": 210, "1": 82}, "flags": {}, "order": 1, "mode": 0, "outputs": [{"name": "FLOAT", "type": "FLOAT", "links": [69], "slot_index": 0, "widget": {"name": "elevation"}, "label": "FLOAT"}], "properties": {"Run widget replace on values": false}, "widgets_values": [0, "fixed"]}, {"id": 53, "type": "Range(Num Steps) - Float", "pos": [201.24009997558593, 829.9400007324214], "size": {"0": 315, "1": 126}, "flags": {}, "order": 2, "mode": 0, "outputs": [{"name": "range", "type": "FLOAT", "links": [74], "shape": 6, "label": "range", "slot_index": 0}, {"name": "range_sizes", "type": "INT", "links": null, "shape": 6, "label": "range_sizes"}], "properties": {"Node name for S&R": "Range(Num Steps) - Float"}, "widgets_values": [0, 330, 12]}, {"id": 84, "type": "CheckpointLoaderSimple", "pos": [202.24009997558593, 1021.9400007324211], "size": {"0": 321.11956787109375, "1": 311.5102233886719}, "flags": {}, "order": 3, "mode": 0, "outputs": [{"name": "MODEL", "type": "MODEL", "links": [128], "shape": 3, "label": "\u6a21\u578b"}, {"name": "CLIP", "type": "CLIP", "links": [138], "shape": 3, "label": "CLIP", "slot_index": 1}, {"name": "VAE", "type": "VAE", "links": [141, 170], "shape": 3, "label": "VAE"}], "properties": {"Node name for S&R": "CheckpointLoaderSimple"}, "widgets_values": ["realcartoonPixar_v5.safetensors"]}, {"id": 88, "type": "CLIPSetLastLayer", "pos": [560.2400999755857, 1250.9400007324211], "size": {"0": 315, "1": 58}, "flags": {}, "order": 17, "mode": 0, "inputs": [{"name": "clip", "type": "CLIP", "link": 140, "label": "CLIP"}], "outputs": [{"name": "CLIP", "type": "CLIP", "links": [], "shape": 3, "label": "CLIP", "slot_index": 0}], "properties": {"Node name for S&R": "CLIPSetLastLayer"}, "widgets_values": [-1]}, {"id": 36, "type": "LoraLoaderModelOnly", "pos": [578.2400999755857, 312.9400007324219], "size": {"0": 315, "1": 82}, "flags": {}, "order": 14, "mode": 0, "inputs": [{"name": "model", "type": "MODEL", "link": 61, "label": "\u6a21\u578b"}], "outputs": [{"name": "MODEL", "type": "MODEL", "links": [62], "shape": 3, "label": "\u6a21\u578b", "slot_index": 0}], "properties": {"Node name for S&R": "LoraLoaderModelOnly"}, "widgets_values": ["\u52a0\u901fLORA\\LCM_LoRA_Weights_SD15.safetensors", 1]}, {"id": 26, "type": "StableZero123_Conditioning", "pos": [568.2400999755857, 472.9400007324217], "size": {"0": 315, "1": 194}, "flags": {}, "order": 30, "mode": 0, "inputs": [{"name": "clip_vision", "type": "CLIP_VISION", "link": 50, "label": "CLIP\u89c6\u89c9"}, {"name": "init_image", "type": "IMAGE", "link": 106, "label": "\u56fe\u50cf"}, {"name": "vae", "type": "VAE", "link": 52, "label": "vae"}, {"name": "elevation", "type": "FLOAT", "link": 69, "widget": {"name": "elevation"}, "label": "\u4fef\u4ef0\u89d2", "slot_index": 3}, {"name": "azimuth", "type": "FLOAT", "link": 74, "widget": {"name": "azimuth"}, "slot_index": 4, "label": "\u65b9\u4f4d\u89d2"}, {"name": "width", "type": "INT", "link": 92, "widget": {"name": "width"}, "label": "\u5bbd\u5ea6"}, {"name": "height", "type": "INT", "link": 93, "widget": {"name": "height"}, "label": "\u9ad8\u5ea6"}], "outputs": [{"name": "positive", "type": "CONDITIONING", "links": [53], "shape": 3, "slot_index": 0, "label": "\u6b63\u9762\u6761\u4ef6"}, {"name": "negative", "type": "CONDITIONING", "links": [54], "shape": 3, "slot_index": 1, "label": "\u8d1f\u9762\u6761\u4ef6"}, {"name": "latent", "type": "LATENT", "links": [80], "shape": 3, "slot_index": 2, "label": "Latent"}], "properties": {"Node name for S&R": "StableZero123_Conditioning"}, "widgets_values": [256, 256, 1, 0, 180]}, {"id": 83, "type": "Upscale Model Loader", "pos": [567.2400999755857, 717.9400007324214], "size": {"0": 310.64947509765625, "1": 136.35023498535156}, "flags": {}, "order": 4, "mode": 0, "outputs": [{"name": "UPSCALE_MODEL", "type": "UPSCALE_MODEL", "links": [118], "shape": 3, "label": "\u653e\u5927\u6a21\u578b"}, {"name": "MODEL_NAME_TEXT", "type": "STRING", "links": null, "shape": 3, "label": "\u6a21\u578b\u540d\u79f0\u6587\u672c"}], "properties": {"Node name for S&R": "Upscale Model Loader"}, "widgets_values": ["4x-UltraSharp.pth"]}, {"id": 3, "type": "KSampler", "pos": [918.2400999755855, 452.9400007324219], "size": {"0": 387.7695007324219, "1": 846.8402099609375}, "flags": {}, "order": 31, "mode": 0, "inputs": [{"name": "model", "type": "MODEL", "link": 62, "label": "\u6a21\u578b"}, {"name": "positive", "type": "CONDITIONING", "link": 53, "label": "\u6b63\u9762\u6761\u4ef6"}, {"name": "negative", "type": "CONDITIONING", "link": 54, "label": "\u8d1f\u9762\u6761\u4ef6"}, {"name": "latent_image", "type": "LATENT", "link": 80, "label": "Latent"}], "outputs": [{"name": "LATENT", "type": "LATENT", "links": [89], "slot_index": 0, "label": "Latent"}], "properties": {"Node name for S&R": "KSampler"}, "widgets_values": [183189615600647, "randomize", 6, 1.5, "euler_ancestral", "normal", 1]}, {"id": 64, "type": "GetImageSize", "pos": [191, 589], "size": {"0": 344.2195129394531, "1": 46}, "flags": {}, "order": 29, "mode": 0, "inputs": [{"name": "image", "type": "IMAGE", "link": 167, "label": "\u56fe\u50cf", "slot_index": 0}], "outputs": [{"name": "width", "type": "INT", "links": [92], "shape": 3, "label": "\u5bbd\u5ea6", "slot_index": 0}, {"name": "height", "type": "INT", "links": [93], "shape": 3, "label": "\u9ad8\u5ea6", "slot_index": 1}], "properties": {"Node name for S&R": "GetImageSize"}}, {"id": 85, "type": "LoraLoader", "pos": [558, 938], "size": {"0": 315, "1": 126}, "flags": {}, "order": 15, "mode": 0, "inputs": [{"name": "model", "type": "MODEL", "link": 128, "label": "\u6a21\u578b", "slot_index": 0}, {"name": "clip", "type": "CLIP", "link": 138, "label": "CLIP", "slot_index": 1}], "outputs": [{"name": "MODEL", "type": "MODEL", "links": [139, 168], "shape": 3, "label": "\u6a21\u578b", "slot_index": 0}, {"name": "CLIP", "type": "CLIP", "links": [140, 169], "shape": 3, "label": "CLIP", "slot_index": 1}], "properties": {"Node name for S&R": "LoraLoader"}, "widgets_values": ["\u52a0\u901fLORA\\LCM_LoRA_Weights_SD15.safetensors", 1, 1]}, {"id": 8, "type": "VAEDecode", "pos": [942, 343], "size": {"0": 330.25958251953125, "1": 53.24025344848633}, "flags": {}, "order": 32, "mode": 0, "inputs": [{"name": "samples", "type": "LATENT", "link": 89, "label": "Latent"}, {"name": "vae", "type": "VAE", "link": 26, "label": "VAE"}], "outputs": [{"name": "IMAGE", "type": "IMAGE", "links": [122], "slot_index": 0, "label": "\u56fe\u50cf"}], "properties": {"Node name for S&R": "VAEDecode"}}, {"id": 100, "type": "FaceDetailer", "pos": [2092.036196944312, 1492.0517779168154], "size": {"0": 603.496826171875, "1": 1080.5946044921875}, "flags": {}, "order": 34, "mode": 4, "inputs": [{"name": "image", "type": "IMAGE", "link": 171, "label": "\u56fe\u50cf"}, {"name": "model", "type": "MODEL", "link": 168, "label": "\u6a21\u578b", "slot_index": 1}, {"name": "clip", "type": "CLIP", "link": 169, "label": "CLIP", "slot_index": 2}, {"name": "vae", "type": "VAE", "link": 170, "label": "VAE", "slot_index": 3}, {"name": "positive", "type": "CONDITIONING", "link": 173, "label": "\u6b63\u9762\u6761\u4ef6"}, {"name": "negative", "type": "CONDITIONING", "link": 174, "label": "\u8d1f\u9762\u6761\u4ef6", "slot_index": 5}, {"name": "bbox_detector", "type": "BBOX_DETECTOR", "link": 179, "label": "BBox\u68c0\u6d4b", "slot_index": 6}, {"name": "sam_model_opt", "type": "SAM_MODEL", "link": 177, "label": "SAM\u6a21\u578b", "slot_index": 7}, {"name": "segm_detector_opt", "type": "SEGM_DETECTOR", "link": 178, "label": "Segm\u68c0\u6d4b", "slot_index": 8}, {"name": "detailer_hook", "type": "DETAILER_HOOK", "link": 180, "label": "\u7ec6\u5316\u7ea6\u675f", "slot_index": 9}], "outputs": [{"name": "image", "type": "IMAGE", "links": [172], "shape": 3, "label": "\u56fe\u50cf", "slot_index": 0}, {"name": "cropped_refined", "type": "IMAGE", "links": null, "shape": 6, "label": "\u7ec6\u5316\u56fe\u50cf", "slot_index": 1}, {"name": "cropped_enhanced_alpha", "type": "IMAGE", "links": null, "shape": 6, "label": "\u7ec6\u5316\u90e8\u5206"}, {"name": "mask", "type": "MASK", "links": null, "shape": 3, "label": "\u906e\u7f69"}, {"name": "detailer_pipe", "type": "DETAILER_PIPE", "links": null, "shape": 3, "label": "\u7ec6\u5316\u8282\u70b9\u675f"}, {"name": "cnet_images", "type": "IMAGE", "links": null, "shape": 6, "label": "ControlNet\u56fe\u50cf"}], "properties": {"Node name for S&R": "FaceDetailer"}, "widgets_values": [256, true, 768, 554189788855103, "randomize", 20, 8, "euler", "normal", 0.5, 5, true, true, 0.5, 10, 3, "center-1", 0, 0.93, 0, 0.7, "False", 10, "", 1]}, {"id": 103, "type": "SAMLoader", "pos": [1743.3190395771242, 1615.9137979924378], "size": {"0": 263.7709655761719, "1": 114.42072296142578}, "flags": {}, "order": 5, "mode": 4, "outputs": [{"name": "SAM_MODEL", "type": "SAM_MODEL", "links": [177], "shape": 3, "label": "SAM\u6a21\u578b"}], "properties": {"Node name for S&R": "SAMLoader"}, "widgets_values": ["sam_vit_b_01ec64.pth", "Prefer GPU"]}, {"id": 104, "type": "UltralyticsDetectorProvider", "pos": [1741.3190395771242, 1774.9137979924378], "size": {"0": 260.452880859375, "1": 113.95054626464844}, "flags": {}, "order": 6, "mode": 4, "outputs": [{"name": "BBOX_DETECTOR", "type": "BBOX_DETECTOR", "links": [179], "shape": 3, "label": "BBox\u68c0\u6d4b"}, {"name": "SEGM_DETECTOR", "type": "SEGM_DETECTOR", "links": [178], "shape": 3, "label": "SEGM\u68c0\u6d4b"}], "properties": {"Node name for S&R": "UltralyticsDetectorProvider"}, "widgets_values": ["bbox/face_yolov8m.pt"]}, {"id": 105, "type": "CoreMLDetailerHookProvider", "pos": [1752.3190395771242, 1938.9137979924378], "size": {"0": 259.7977600097656, "1": 114.00162506103516}, "flags": {}, "order": 7, "mode": 4, "outputs": [{"name": "DETAILER_HOOK", "type": "DETAILER_HOOK", "links": [180], "shape": 3, "label": "\u7ec6\u5316\u7ea6\u675f"}], "properties": {"Node name for S&R": "CoreMLDetailerHookProvider"}, "widgets_values": ["512x512"]}, {"id": 109, "type": "Note", "pos": [1687.3190395771242, 2161.913797992438], "size": {"0": 376.35479736328125, "1": 262.280517578125}, "flags": {}, "order": 8, "mode": 0, "properties": {"text": ""}, "widgets_values": ["If it is related to characters, please open the facial restoration process."], "color": "#432", "bgcolor": "#653"}, {"id": 70, "type": "CLIPTextEncode", "pos": [-1300, 1162], "size": {"0": 332.01611328125, "1": 184.1253204345703}, "flags": {}, "order": 20, "mode": 0, "inputs": [{"name": "clip", "type": "CLIP", "link": 143, "label": "CLIP", "slot_index": 0}], "outputs": [{"name": "CONDITIONING", "type": "CONDITIONING", "links": [120, 174, 229], "slot_index": 0, "label": "\u6761\u4ef6"}], "properties": {"Node name for S&R": "CLIPTextEncode"}, "widgets_values": ["embedding:bad_pictures, "]}, {"id": 67, "type": "CheckpointLoaderSimple", "pos": [-1295, 678], "size": {"0": 325.55206298828125, "1": 186.7132568359375}, "flags": {}, "order": 9, "mode": 0, "outputs": [{"name": "MODEL", "type": "MODEL", "links": [102], "slot_index": 0, "label": "\u6a21\u578b"}, {"name": "CLIP", "type": "CLIP", "links": [103], "slot_index": 1, "label": "CLIP"}, {"name": "VAE", "type": "VAE", "links": [101, 222], "slot_index": 2, "label": "VAE"}], "properties": {"Node name for S&R": "CheckpointLoaderSimple"}, "widgets_values": ["SD1.5\\3D\u6548\u679csdvn53dcutewave_v10.safetensors"]}, {"id": 72, "type": "LoraLoader", "pos": [-1291, 326], "size": {"0": 320.55206298828125, "1": 301.67266845703125}, "flags": {}, "order": 16, "mode": 0, "inputs": [{"name": "model", "type": "MODEL", "link": 102, "label": "\u6a21\u578b"}, {"name": "clip", "type": "CLIP", "link": 103, "label": "CLIP"}], "outputs": [{"name": "MODEL", "type": "MODEL", "links": [111], "shape": 3, "slot_index": 0, "label": "\u6a21\u578b"}, {"name": "CLIP", "type": "CLIP", "links": [131, 143], "shape": 3, "slot_index": 1, "label": "CLIP"}], "properties": {"Node name for S&R": "LoraLoader"}, "widgets_values": ["\u52a0\u901fLORA\\LCM_LoRA_Weights_SD15.safetensors", 1, 1]}, {"id": 76, "type": "IPAdapterApply", "pos": [-936, 450], "size": {"0": 317.1123046875, "1": 269.61181640625}, "flags": {}, "order": 18, "mode": 0, "inputs": [{"name": "ipadapter", "type": "IPADAPTER", "link": 110, "label": "IP\u9002\u914d", "slot_index": 0}, {"name": "clip_vision", "type": "CLIP_VISION", "link": 112, "label": "CLIP\u89c6\u89c9", "slot_index": 1}, {"name": "image", "type": "IMAGE", "link": 109, "label": "\u56fe\u50cf", "slot_index": 2}, {"name": "model", "type": "MODEL", "link": 111, "label": "\u6a21\u578b", "slot_index": 3}, {"name": "attn_mask", "type": "MASK", "link": null, "label": "\u5173\u6ce8\u5c42\u906e\u7f69"}], "outputs": [{"name": "MODEL", "type": "MODEL", "links": [113], "shape": 3, "label": "\u6a21\u578b", "slot_index": 0}], "properties": {"Node name for S&R": "IPAdapterApply"}, "widgets_values": [1, 0, "original", 0, 1, false]}, {"id": 73, "type": "ModelSamplingDiscrete", "pos": [-928, 316], "size": {"0": 315, "1": 82}, "flags": {}, "order": 21, "mode": 0, "inputs": [{"name": "model", "type": "MODEL", "link": 113, "label": "\u6a21\u578b"}], "outputs": [{"name": "MODEL", "type": "MODEL", "links": [94], "shape": 3, "slot_index": 0, "label": "MODEL"}], "properties": {"Node name for S&R": "ModelSamplingDiscrete"}, "widgets_values": ["lcm", false]}, {"id": 78, "type": "IPAdapterModelLoader", "pos": [-593, 454], "size": {"0": 280.0566711425781, "1": 117.27640533447266}, "flags": {}, "order": 10, "mode": 0, "outputs": [{"name": "IPADAPTER", "type": "IPADAPTER", "links": [110], "shape": 3, "label": "IP\u9002\u914d"}], "properties": {"Node name for S&R": "IPAdapterModelLoader"}, "widgets_values": ["ip-adapter-plus_sd15.bin"]}, {"id": 79, "type": "CLIPVisionLoader", "pos": [-598, 615], "size": {"0": 285.33026123046875, "1": 114.5700912475586}, "flags": {}, "order": 11, "mode": 0, "outputs": [{"name": "CLIP_VISION", "type": "CLIP_VISION", "links": [112], "shape": 3, "label": "CLIP\u89c6\u89c9"}], "properties": {"Node name for S&R": "CLIPVisionLoader"}, "widgets_values": ["SD1.5\\2pytorch_model.bin"]}, {"id": 63, "type": "ImageScaleBy", "pos": [187.24009997558602, 459.9400007324219], "size": {"0": 354.26953125, "1": 82}, "flags": {}, "order": 28, "mode": 0, "inputs": [{"name": "image", "type": "IMAGE", "link": 193, "label": "\u56fe\u50cf", "slot_index": 0}], "outputs": [{"name": "IMAGE", "type": "IMAGE", "links": [106, 167], "shape": 3, "label": "\u56fe\u50cf", "slot_index": 0}], "properties": {"Node name for S&R": "ImageScaleBy"}, "widgets_values": ["nearest-exact", 0.5]}, {"id": 71, "type": "VAEDecode", "pos": [-595, 333], "size": {"0": 290.4878845214844, "1": 56.625732421875}, "flags": {}, "order": 26, "mode": 0, "inputs": [{"name": "samples", "type": "LATENT", "link": 100, "label": "Latent"}, {"name": "vae", "type": "VAE", "link": 101, "slot_index": 1, "label": "VAE"}], "outputs": [{"name": "IMAGE", "type": "IMAGE", "links": [107, 193], "slot_index": 0, "label": "\u56fe\u50cf"}], "properties": {"Node name for S&R": "VAEDecode"}}, {"id": 80, "type": "UltimateSDUpscale", "pos": [1351, 310], "size": {"0": 327.0533142089844, "1": 1050.10009765625}, "flags": {}, "order": 33, "mode": 4, "inputs": [{"name": "image", "type": "IMAGE", "link": 122, "label": "\u56fe\u50cf"}, {"name": "model", "type": "MODEL", "link": 139, "label": "\u6a21\u578b", "slot_index": 1}, {"name": "positive", "type": "CONDITIONING", "link": 119, "label": "\u6b63\u9762\u6761\u4ef6", "slot_index": 2}, {"name": "negative", "type": "CONDITIONING", "link": 120, "label": "\u8d1f\u9762\u6761\u4ef6", "slot_index": 3}, {"name": "vae", "type": "VAE", "link": 141, "label": "VAE", "slot_index": 4}, {"name": "upscale_model", "type": "UPSCALE_MODEL", "link": 118, "label": "\u653e\u5927\u6a21\u578b", "slot_index": 5}], "outputs": [{"name": "IMAGE", "type": "IMAGE", "links": [171], "shape": 3, "label": "\u56fe\u50cf", "slot_index": 0}], "properties": {"Node name for S&R": "UltimateSDUpscale"}, "widgets_values": [2, 114959403726222, "randomize", 7, 1.3, "euler", "normal", 0.2, "Chess", 512, 512, 8, 32, "None", 1, 64, 8, 16, true, false]}, {"id": 74, "type": "PreviewImage", "pos": [-315, 843], "size": {"0": 365.58245849609375, "1": 506.08575439453125}, "flags": {}, "order": 27, "mode": 0, "inputs": [{"name": "images", "type": "IMAGE", "link": 107, "label": "\u56fe\u50cf"}], "properties": {"Node name for S&R": "PreviewImage"}}, {"id": 75, "type": "Image Save", "pos": [1732, 309], "size": {"0": 919.7828369140625, "1": 1054.5421142578125}, "flags": {}, "order": 35, "mode": 0, "inputs": [{"name": "images", "type": "IMAGE", "link": 172, "label": "images"}], "properties": {"Node name for S&R": "Image Save"}, "widgets_values": ["[time(%Y-%m-%d)]", "3d", "_", 4, "false", "png", 100, "false", "false", "false", "true", "true", "true"]}, {"id": 66, "type": "KSampler", "pos": [-274, 314], "size": {"0": 315, "1": 474}, "flags": {"collapsed": false}, "order": 25, "mode": 0, "inputs": [{"name": "model", "type": "MODEL", "link": 94, "label": "\u6a21\u578b"}, {"name": "positive", "type": "CONDITIONING", "link": 219, "label": "\u6b63\u9762\u6761\u4ef6"}, {"name": "negative", "type": "CONDITIONING", "link": 220, "label": "\u8d1f\u9762\u6761\u4ef6"}, {"name": "latent_image", "type": "LATENT", "link": 218, "label": "Latent", "slot_index": 3}], "outputs": [{"name": "LATENT", "type": "LATENT", "links": [100], "slot_index": 0, "label": "Latent"}], "properties": {"Node name for S&R": "KSampler"}, "widgets_values": [433228791219439, "randomize", 7, 1.3, "lcm", "sgm_uniform", 0.9]}, {"id": 111, "type": "PreviewImage", "pos": [-175, 1499], "size": {"0": 203.86631774902344, "1": 246}, "flags": {}, "order": 24, "mode": 0, "inputs": [{"name": "images", "type": "IMAGE", "link": 215, "label": "\u56fe\u50cf"}], "properties": {"Node name for S&R": "PreviewImage"}}, {"id": 116, "type": "workflow/lineart", "pos": [-517, 1477], "size": {"0": 315, "1": 318}, "flags": {}, "order": 23, "mode": 0, "inputs": [{"name": "\u56fe\u50cf", "type": "IMAGE", "link": 221, "label": "\u56fe\u50cf"}, {"name": "VAE", "type": "VAE", "link": 222, "label": "VAE"}, {"name": "\u6b63\u9762\u6761\u4ef6", "type": "CONDITIONING", "link": 225, "label": "\u6b63\u9762\u6761\u4ef6"}, {"name": "\u8d1f\u9762\u6761\u4ef6", "type": "CONDITIONING", "link": 226, "label": "\u8d1f\u9762\u6761\u4ef6"}, {"name": "\u906e\u7f69", "type": "MASK", "link": null, "label": "\u906e\u7f69"}, {"name": "\u5e27\u95f4\u9694", "type": "TIMESTEP_KEYFRAME", "link": null, "label": "\u5e27\u95f4\u9694"}, {"name": "", "type": "LATENT_KEYFRAME", "link": null, "label": ""}, {"name": "weights_override", "type": "CONTROL_NET_WEIGHTS", "link": null, "label": "weights_override"}], "outputs": [{"name": "\u56fe\u50cf", "type": "IMAGE", "links": [215], "shape": 3, "label": "\u56fe\u50cf"}, {"name": "Latent", "type": "LATENT", "links": [218], "shape": 3, "label": "Latent"}, {"name": "\u6b63\u9762\u6761\u4ef6", "type": "CONDITIONING", "links": [219], "shape": 3, "label": "\u6b63\u9762\u6761\u4ef6"}, {"name": "\u8d1f\u9762\u6761\u4ef6", "type": "CONDITIONING", "links": [220], "shape": 3, "label": "\u8d1f\u9762\u6761\u4ef6"}], "properties": {"Node name for S&R": "workflow/lineart"}, "widgets_values": ["control_v11p_sd15_lineart.pth", "LineArtPreprocessor", 512, 1, 0, 1]}, {"id": 117, "type": "workflow/tile", "pos": [-1280, 1486], "size": {"0": 556.800048828125, "1": 318}, "flags": {}, "order": 22, "mode": 0, "inputs": [{"name": "\u5e27\u95f4\u9694", "type": "TIMESTEP_KEYFRAME", "link": null, "label": "\u5e27\u95f4\u9694"}, {"name": "\u56fe\u50cf", "type": "IMAGE", "link": 227, "label": "\u56fe\u50cf"}, {"name": "\u6b63\u9762\u6761\u4ef6", "type": "CONDITIONING", "link": 228, "label": "\u6b63\u9762\u6761\u4ef6"}, {"name": "\u8d1f\u9762\u6761\u4ef6", "type": "CONDITIONING", "link": 229, "label": "\u8d1f\u9762\u6761\u4ef6"}, {"name": "\u906e\u7f69", "type": "MASK", "link": null, "label": "\u906e\u7f69"}, {"name": "ACN_AdvancedControlNetApply timestep_kf", "type": "TIMESTEP_KEYFRAME", "link": null, "label": "ACN_AdvancedControlNetApply timestep_kf"}, {"name": "", "type": "LATENT_KEYFRAME", "link": null, "label": ""}, {"name": "weights_override", "type": "CONTROL_NET_WEIGHTS", "link": null, "label": "weights_override"}], "outputs": [{"name": "\u6b63\u9762\u6761\u4ef6", "type": "CONDITIONING", "links": [225], "shape": 3, "label": "\u6b63\u9762\u6761\u4ef6"}, {"name": "\u8d1f\u9762\u6761\u4ef6", "type": "CONDITIONING", "links": [226], "shape": 3, "label": "\u8d1f\u9762\u6761\u4ef6"}], "properties": {"Node name for S&R": "workflow/tile"}, "widgets_values": ["control_v11f1e_sd15_tile.pth", "TilePreprocessor", 512, 1, 0, 1]}, {"id": 69, "type": "CLIPTextEncode", "pos": [-1299, 912], "size": {"0": 330.01611328125, "1": 202.91305541992188}, "flags": {}, "order": 19, "mode": 0, "inputs": [{"name": "clip", "type": "CLIP", "link": 131, "label": "CLIP", "slot_index": 0}], "outputs": [{"name": "CONDITIONING", "type": "CONDITIONING", "links": [119, 173, 228], "slot_index": 0, "label": "\u6761\u4ef6"}], "properties": {"Node name for S&R": "CLIPTextEncode"}, "widgets_values": ["1girl, solo, looking_at_viewer, short_hair, brown_hair, navel, brown_eyes, standing, full_body, barefoot, midriff, pants, grey_background, lips, crop_top, tank_top, realistic, leggings, capri_pants, yoga_pants"]}, {"id": 94, "type": "Note", "pos": [-1656, 1548], "size": {"0": 301.219482421875, "1": 174.066162109375}, "flags": {}, "order": 12, "mode": 0, "properties": {"text": ""}, "widgets_values": ["If you don't have high requirements for the consistency of the uploaded images, please do not open it as it seems to affect the final result."], "color": "#432", "bgcolor": "#653"}, {"id": 77, "type": "LoadImage", "pos": [-936, 770], "size": {"0": 585.4022827148438, "1": 590.72265625}, "flags": {}, "order": 13, "mode": 0, "outputs": [{"name": "IMAGE", "type": "IMAGE", "links": [109, 221, 227], "shape": 3, "label": "\u56fe\u50cf", "slot_index": 0}, {"name": "MASK", "type": "MASK", "links": [], "shape": 3, "label": "\u906e\u7f69", "slot_index": 1}], "properties": {"Node name for S&R": "LoadImage"}, "widgets_values": ["L4D1113ENDDVADLCWGEJKVNV6XRP3WK6Q8_1000x1000 (10).jpg", "image"]}], "links": [[26, 15, 2, 8, 1, "VAE"], [50, 15, 1, 26, 0, "CLIP_VISION"], [52, 15, 2, 26, 2, "VAE"], [53, 26, 0, 3, 1, "CONDITIONING"], [54, 26, 1, 3, 2, "CONDITIONING"], [61, 15, 0, 36, 0, "MODEL"], [62, 36, 0, 3, 0, "MODEL"], [69, 32, 0, 26, 3, "FLOAT"], [74, 53, 0, 26, 4, "FLOAT"], [80, 26, 2, 3, 3, "LATENT"], [89, 3, 0, 8, 0, "LATENT"], [92, 64, 0, 26, 5, "INT"], [93, 64, 1, 26, 6, "INT"], [94, 73, 0, 66, 0, "MODEL"], [100, 66, 0, 71, 0, "LATENT"], [101, 67, 2, 71, 1, "VAE"], [102, 67, 0, 72, 0, "MODEL"], [103, 67, 1, 72, 1, "CLIP"], [106, 63, 0, 26, 1, "IMAGE"], [107, 71, 0, 74, 0, "IMAGE"], [109, 77, 0, 76, 2, "IMAGE"], [110, 78, 0, 76, 0, "IPADAPTER"], [111, 72, 0, 76, 3, "MODEL"], [112, 79, 0, 76, 1, "CLIP_VISION"], [113, 76, 0, 73, 0, "MODEL"], [118, 83, 0, 80, 5, "UPSCALE_MODEL"], [119, 69, 0, 80, 2, "CONDITIONING"], [120, 70, 0, 80, 3, "CONDITIONING"], [122, 8, 0, 80, 0, "IMAGE"], [128, 84, 0, 85, 0, "MODEL"], [131, 72, 1, 69, 0, "CLIP"], [138, 84, 1, 85, 1, "CLIP"], [139, 85, 0, 80, 1, "MODEL"], [140, 85, 1, 88, 0, "CLIP"], [141, 84, 2, 80, 4, "VAE"], [143, 72, 1, 70, 0, "CLIP"], [167, 63, 0, 64, 0, "IMAGE"], [168, 85, 0, 100, 1, "MODEL"], [169, 85, 1, 100, 2, "CLIP"], [170, 84, 2, 100, 3, "VAE"], [171, 80, 0, 100, 0, "IMAGE"], [172, 100, 0, 75, 0, "IMAGE"], [173, 69, 0, 100, 4, "CONDITIONING"], [174, 70, 0, 100, 5, "CONDITIONING"], [177, 103, 0, 100, 7, "SAM_MODEL"], [178, 104, 1, 100, 8, "SEGM_DETECTOR"], [179, 104, 0, 100, 6, "BBOX_DETECTOR"], [180, 105, 0, 100, 9, "DETAILER_HOOK"], [193, 71, 0, 63, 0, "IMAGE"], [215, 116, 0, 111, 0, "IMAGE"], [218, 116, 1, 66, 3, "LATENT"], [219, 116, 2, 66, 1, "CONDITIONING"], [220, 116, 3, 66, 2, "CONDITIONING"], [221, 77, 0, 116, 0, "IMAGE"], [222, 67, 2, 116, 1, "VAE"], [225, 117, 0, 116, 2, "CONDITIONING"], [226, 117, 1, 116, 3, "CONDITIONING"], [227, 77, 0, 117, 1, "IMAGE"], [228, 69, 0, 117, 2, "CONDITIONING"], [229, 70, 0, 117, 3, "CONDITIONING"]], "groups": [{"title": "text to image", "bounding": [-1312, 231, 1379, 1133], "color": "#3f789e", "font_size": 24, "locked": false}, {"title": "Image to 3d", "bounding": [165, 227, 2554, 1160], "color": "#3f789e", "font_size": 24, "locked": false}, {"title": "\u9762\u90e8\u4fee\u590d", "bounding": [1638, 1405, 1079, 1184], "color": "#3f789e", "font_size": 24, "locked": false}, {"title": "control network", "bounding": [-1308, 1391, 1364, 527], "color": "#3f789e", "font_size": 24, "locked": false}], "config": {}, "extra": {"groupNodes": {"contorlet": {"nodes": [{"type": "AIO_Preprocessor", "pos": [-895, 978], "size": {"0": 434.543212890625, "1": 82}, "flags": {}, "order": 13, "mode": 0, "inputs": [{"name": "image", "type": "IMAGE", "link": null, "label": "\u56fe\u50cf", "slot_index": 0}], "outputs": [{"name": "IMAGE", "type": "IMAGE", "links": [], "shape": 3, "label": "\u56fe\u50cf", "slot_index": 0}], "properties": {"Node name for S&R": "AIO_Preprocessor"}, "widgets_values": ["LineArtPreprocessor", 512], "index": 0}, {"type": "PreviewImage", "pos": [-891, 1101], "size": {"0": 203.86631774902344, "1": 246}, "flags": {}, "order": 18, "mode": 0, "inputs": [{"name": "images", "type": "IMAGE", "link": null, "label": "\u56fe\u50cf"}], "properties": {"Node name for S&R": "PreviewImage"}, "index": 1}, {"type": "VAEEncode", "pos": [-677, 1109], "size": {"0": 210, "1": 46}, "flags": {}, "order": 19, "mode": 0, "inputs": [{"name": "pixels", "type": "IMAGE", "link": null, "label": "\u56fe\u50cf"}, {"name": "vae", "type": "VAE", "link": null, "label": "VAE", "slot_index": 1}], "outputs": [{"name": "LATENT", "type": "LATENT", "links": [], "shape": 3, "label": "Latent", "slot_index": 0}], "properties": {"Node name for S&R": "VAEEncode"}, "index": 2}], "links": [[null, 0, 0, 0, 77, "IMAGE"], [0, 0, 1, 0, 90, "IMAGE"], [0, 0, 2, 0, 90, "IMAGE"], [null, 2, 2, 1, 67, "VAE"]], "external": [[2, 0, "LATENT"]]}, "lineart": {"nodes": [{"type": "ControlNetLoader", "pos": [-743, 1811], "size": {"0": 315, "1": 58}, "flags": {}, "order": 15, "mode": 0, "outputs": [{"name": "CONTROL_NET", "type": "CONTROL_NET", "links": [], "shape": 3, "label": "ControlNet"}], "properties": {"Node name for S&R": "ControlNetLoader"}, "widgets_values": ["control_v11p_sd15_lineart.pth"], "index": 0}, {"type": "AIO_Preprocessor", "pos": [-380, 1434], "size": {"0": 434.543212890625, "1": 82}, "flags": {}, "order": 19, "mode": 0, "inputs": [{"name": "image", "type": "IMAGE", "link": null, "label": "\u56fe\u50cf", "slot_index": 0}], "outputs": [{"name": "IMAGE", "type": "IMAGE", "links": [], "shape": 3, "label": "\u56fe\u50cf", "slot_index": 0}], "properties": {"Node name for S&R": "AIO_Preprocessor"}, "widgets_values": ["LineArtPreprocessor", 512], "index": 1}, {"type": "VAEEncode", "pos": [-165, 1566], "size": {"0": 210, "1": 46}, "flags": {}, "order": 26, "mode": 0, "inputs": [{"name": "pixels", "type": "IMAGE", "link": null, "label": "\u56fe\u50cf"}, {"name": "vae", "type": "VAE", "link": null, "label": "VAE", "slot_index": 1}], "outputs": [{"name": "LATENT", "type": "LATENT", "links": [], "shape": 3, "label": "Latent", "slot_index": 0}], "properties": {"Node name for S&R": "VAEEncode"}, "index": 2}, {"type": "ACN_AdvancedControlNetApply", "pos": [-770, 1492], "size": {"0": 342.5999755859375, "1": 246}, "flags": {}, "order": 29, "mode": 0, "inputs": [{"name": "positive", "type": "CONDITIONING", "link": null, "label": "\u6b63\u9762\u6761\u4ef6", "slot_index": 0}, {"name": "negative", "type": "CONDITIONING", "link": null, "label": "\u8d1f\u9762\u6761\u4ef6", "slot_index": 1}, {"name": "control_net", "type": "CONTROL_NET", "link": null, "label": "ControlNet", "slot_index": 2}, {"name": "image", "type": "IMAGE", "link": null, "label": "\u56fe\u50cf"}, {"name": "mask_optional", "type": "MASK", "link": null, "label": "\u906e\u7f69"}, {"name": "timestep_kf", "type": "TIMESTEP_KEYFRAME", "link": null, "label": "\u5e27\u95f4\u9694"}, {"name": "latent_kf_override", "type": "LATENT_KEYFRAME", "link": null, "label": ""}, {"name": "weights_override", "type": "CONTROL_NET_WEIGHTS", "link": null}], "outputs": [{"name": "positive", "type": "CONDITIONING", "links": [], "shape": 3, "label": "\u6b63\u9762\u6761\u4ef6", "slot_index": 0}, {"name": "negative", "type": "CONDITIONING", "links": [], "shape": 3, "label": "\u8d1f\u9762\u6761\u4ef6", "slot_index": 1}], "properties": {"Node name for S&R": "ACN_AdvancedControlNetApply"}, "widgets_values": [1, 0, 1], "index": 3}], "links": [[null, 0, 1, 0, 77, "IMAGE"], [1, 0, 2, 0, 110, "IMAGE"], [null, 2, 2, 1, 67, "VAE"], [null, 0, 3, 0, 107, "CONDITIONING"], [null, 1, 3, 1, 107, "CONDITIONING"], [0, 0, 3, 2, 114, "CONTROL_NET"], [1, 0, 3, 3, 110, "IMAGE"]], "external": [[1, 0, "IMAGE"], [2, 0, "LATENT"], [3, 0, "CONDITIONING"], [3, 1, "CONDITIONING"]]}, "tile": {"nodes": [{"type": "ControlNetLoaderAdvanced", "pos": [-1290, 1473], "size": {"0": 338.1592102050781, "1": 75.21498107910156}, "flags": {}, "order": 13, "mode": 0, "inputs": [{"name": "timestep_keyframe", "type": "TIMESTEP_KEYFRAME", "link": null, "label": "\u5e27\u95f4\u9694"}], "outputs": [{"name": "CONTROL_NET", "type": "CONTROL_NET", "links": [], "shape": 3, "label": "ControlNet", "slot_index": 0}], "properties": {"Node name for S&R": "ControlNetLoaderAdvanced"}, "widgets_values": ["control_v11f1e_sd15_tile.pth"], "index": 0}, {"type": "AIO_Preprocessor", "pos": [-1789, 1406], "size": {"0": 434.543212890625, "1": 82}, "flags": {}, "order": 18, "mode": 0, "inputs": [{"name": "image", "type": "IMAGE", "link": null, "label": "\u56fe\u50cf", "slot_index": 0}], "outputs": [{"name": "IMAGE", "type": "IMAGE", "links": [], "shape": 3, "label": "\u56fe\u50cf", "slot_index": 0}], "properties": {"Node name for S&R": "AIO_Preprocessor"}, "widgets_values": ["TilePreprocessor", 512], "index": 1}, {"type": "ACN_AdvancedControlNetApply", "pos": [-1298, 1611], "size": {"0": 342.5999755859375, "1": 246}, "flags": {}, "order": 24, "mode": 0, "inputs": [{"name": "positive", "type": "CONDITIONING", "link": null, "label": "\u6b63\u9762\u6761\u4ef6", "slot_index": 0}, {"name": "negative", "type": "CONDITIONING", "link": null, "label": "\u8d1f\u9762\u6761\u4ef6", "slot_index": 1}, {"name": "control_net", "type": "CONTROL_NET", "link": null, "label": "ControlNet"}, {"name": "image", "type": "IMAGE", "link": null, "label": "\u56fe\u50cf", "slot_index": 3}, {"name": "mask_optional", "type": "MASK", "link": null, "label": "\u906e\u7f69"}, {"name": "timestep_kf", "type": "TIMESTEP_KEYFRAME", "link": null, "label": "\u5e27\u95f4\u9694"}, {"name": "latent_kf_override", "type": "LATENT_KEYFRAME", "link": null, "label": ""}, {"name": "weights_override", "type": "CONTROL_NET_WEIGHTS", "link": null}], "outputs": [{"name": "positive", "type": "CONDITIONING", "links": [], "shape": 3, "label": "\u6b63\u9762\u6761\u4ef6", "slot_index": 0}, {"name": "negative", "type": "CONDITIONING", "links": [], "shape": 3, "label": "\u8d1f\u9762\u6761\u4ef6", "slot_index": 1}], "properties": {"Node name for S&R": "ACN_AdvancedControlNetApply"}, "widgets_values": [1, 0, 1], "index": 2}], "links": [[null, 0, 1, 0, 77, "IMAGE"], [null, 0, 2, 0, 69, "CONDITIONING"], [null, 0, 2, 1, 70, "CONDITIONING"], [0, 0, 2, 2, 106, "CONTROL_NET"], [1, 0, 2, 3, 115, "IMAGE"]], "external": [[2, 0, "CONDITIONING"], [2, 1, "CONDITIONING"]]}}}, "version": 0.4}